LICENSE
README.md
pyproject.toml
docs/Makefile
docs/conf.py
docs/index.rst
docs/make.bat
docs/requirements.txt
docs/_static/dataset_itp_len_plot.png
docs/_static/dataset_itp_len_plot_bar_row_col.png
docs/_static/dataset_itp_len_plot_row.png
docs/_static/icon_api.svg
docs/_static/icon_case_studies.svg
docs/_static/icon_start.svg
docs/_static/icon_user_guide.svg
docs/_static/itoeprint_tutorial.png
docs/_static/itp_schematic.png
docs/_static/itp_schematic_2codons.png
docs/_static/itp_schematic_custom.png
docs/_static/itpseq_report.pdf
docs/_static/report_page.png
docs/_static/report_pages.jpg
docs/_static/report_tutorial.png
docs/_static/sample_all_logos.png
docs/_static/sample_codon_violin.png
docs/_static/sample_hmap.png
docs/_static/sample_hmap_grid.png
docs/_static/sample_hmap_grid_EPA.png
docs/_static/sample_hmap_pos.png
docs/_static/sample_hmap_pos_nuc.png
docs/_static/sample_itoeprint.png
docs/_static/sample_itoeprint_interactive.png
docs/_static/sample_itoeprint_shades.png
docs/_static/sample_itp_len_plot.png
docs/_static/sample_itp_len_plot_bar.png
docs/_static/sample_logo.png
docs/_static/sample_subset_logo.png
docs/_static/sample_volcano.png
docs/_static/sample_volcano_log10padj.png
docs/_static/sample_volcano_motif.png
docs/_static/sample_volcano_query.png
docs/_static/tcx_subset_logo_query.png
docs/_static/tcx_volcano_query.png
docs/_static/whatis_itpseq_overview.png
docs/_static/whatis_itpseq_workflow.png
docs/_static/css/itpseq.css
docs/api/dataset.rst
docs/api/funcs.rst
docs/api/index.rst
docs/api/replicate.rst
docs/api/sample.rst
docs/api/generated/itpseq.DataSet.DE.rst
docs/api/generated/itpseq.DataSet.infos.rst
docs/api/generated/itpseq.DataSet.itoeprint.rst
docs/api/generated/itpseq.DataSet.itp_len_plot.rst
docs/api/generated/itpseq.DataSet.reorder_samples.rst
docs/api/generated/itpseq.DataSet.report.rst
docs/api/generated/itpseq.DataSet.set_references.rst
docs/api/generated/itpseq.Replicate.get_counts.rst
itpseq-1.0.0.dist-info/METADATA
itpseq-1.0.0.dist-info/WHEEL
itpseq-1.0.0.dist-info/entry_points.txt
itpseq-1.0.0.dist-info/licenses/LICENSE
itpseq-1.0.0.dist-info/RECORD
