Metadata-Version: 2.4
Name: itpseq
Version: 1.0.0
Summary: A tool to process and analyze iTP-Seq datasets
Project-URL: Homepage, https://github.com/t-renault/itpseq
Project-URL: Issues, https://github.com/t-renault/itpseq/issues
Project-URL: Documentation, https://itpseq.readthedocs.io
Author-email: Thibaud Renault <thibaud.renault@u-bordeaux.fr>
License-Expression: GPL-3.0-only
License-File: LICENSE
Keywords: iTP-Seq,inverse toeprinting,ribosome
Classifier: Intended Audience :: Science/Research
Classifier: License :: OSI Approved :: GNU General Public License v3 (GPLv3)
Classifier: Natural Language :: English
Classifier: Operating System :: OS Independent
Classifier: Programming Language :: Python :: 3
Classifier: Topic :: Scientific/Engineering :: Bio-Informatics
Requires-Python: >=3.9
Requires-Dist: dna-features-viewer
Requires-Dist: jinja2
Requires-Dist: logomaker
Requires-Dist: matplotlib
Requires-Dist: natsort
Requires-Dist: numpy
Requires-Dist: pandas
Requires-Dist: pydeseq2
Requires-Dist: regex
Requires-Dist: rich
Requires-Dist: rich-click
Requires-Dist: seaborn
Requires-Dist: weasyprint
